accounts/__init__.py
accounts/apps.py
accounts/forms.py
accounts/models.py
accounts/tasks.py
accounts/tests.py
accounts/tests_celery_tasks.py
accounts/urls.py
accounts/views.py
accounts/migrations/0001_initial.py
accounts/migrations/0002_auto_20190128_1237.py
accounts/migrations/0003_auto_20190201_1840.py
accounts/migrations/0004_account_status.py
accounts/migrations/0005_auto_20190212_1334.py
accounts/migrations/0006_auto_20190212_1708.py
accounts/migrations/0007_email.py
accounts/migrations/0008_account_assigned_to.py
accounts/migrations/0009_auto_20190809_1659.py
accounts/migrations/0010_account_teams.py
accounts/migrations/__init__.py
accounts/templates/accounts.html
accounts/templates/create_account.html
accounts/templates/create_mail_accounts.html
accounts/templates/error_template.html
accounts/templates/view_account.html
cases/__init__.py
cases/apps.py
cases/forms.py
cases/models.py
cases/tasks.py
cases/tests.py
cases/tests_celery_tasks.py
cases/urls.py
cases/views.py
cases/migrations/0001_initial.py
cases/migrations/0002_auto_20190128_1237.py
cases/migrations/0003_auto_20190212_1334.py
cases/migrations/0004_case_teams.py
cases/migrations/__init__.py
cases/templates/cases.html
cases/templates/cases_list.html
cases/templates/comments.html
cases/templates/create_cases.html
cases/templates/sel_contacts.html
cases/templates/show_case.html
cases/templates/view_case.html
cases/templates/view_contacts.html
common/__init__.py
common/access_decorators_mixins.py
common/admin.py
common/apps.py
common/forms.py
common/models.py
common/status.py
common/tasks.py
common/tests.py
common/tests_celery_tasks.py
common/token_generator.py
common/urls.py
common/utils.py
common/views.py
common/management/__init__.py
common/management/commands/__init__.py
common/management/commands/dotenv.py
common/migrations/0001_initial.py
common/migrations/0002_auto_20190128_1237.py
common/migrations/0003_document.py
common/migrations/0004_attachments_case.py
krynegger_crm-10.2.5.dist-info/LICENSE
krynegger_crm-10.2.5.dist-info/METADATA
krynegger_crm-10.2.5.dist-info/WHEEL
krynegger_crm-10.2.5.dist-info/top_level.txt
krynegger_crm-10.2.5.dist-info/RECORD
